vdatafeed/__init__.py
vdatafeed/config.py
vdatafeed/datafeed.py
vdatafeed/enum_datafeed.py
vdatafeed/interface_datafeed_api.py
vdatafeed/interface_datafeed_hub.py
vdatafeed/ssi/__init__.py
vdatafeed/ssi/api.py
vdatafeed/ssi/constant.py
vdatafeed/ssi/hub.py
vdatafeed/ssi/model.py
vdatafeed/utils/__init__.py
vdatafeed/utils/enum_handler.py
vdatafeed/utils/jwt_handler.py
vdatafeed/utils/model_handler.py
vdatafeed/utils/request_handler.py
vdatafeed/utils/socket_handler.py
vdatafeed-1.1.9.dist-info/LICENSE
vdatafeed-1.1.9.dist-info/METADATA
vdatafeed-1.1.9.dist-info/WHEEL
vdatafeed-1.1.9.dist-info/RECORD
