Metadata-Version: 2.1
Name: vdatafeed
Version: 1.1.9
Summary: vDatafeed: A Python wrapper for Viet Nam Datafeed API
Home-page: https://quant.vn
License: MIT
Author: thync
Author-email: thync@outlook.com
Requires-Python: >=3.9,<4.0
Classifier: Intended Audience :: Developers
Classifier: License :: OSI Approved :: MIT License
Classifier: Operating System :: MacOS
Classifier: Operating System :: Microsoft :: Windows
Classifier: Operating System :: OS Independent
Classifier: Operating System :: POSIX
Classifier: Operating System :: POSIX :: Linux
Classifier: Programming Language :: Python :: 3
Classifier: Programming Language :: Python :: 3.9
Classifier: Programming Language :: Python :: 3.10
Classifier: Programming Language :: Python :: 3.11
Classifier: Programming Language :: Python :: 3.12
Classifier: Topic :: Software Development :: Libraries :: Python Modules
Classifier: Typing :: Typed
Requires-Dist: pydantic (>=2.9.1,<3.0.0)
Requires-Dist: pyjwt (>=2.9.0,<3.0.0)
Requires-Dist: requests (>=2.32.3,<3.0.0)
Requires-Dist: websockets (>=13.0.1,<14.0.0)
Project-URL: Repository, https://github.com/quant-vn/vdatafeed
